rescriptoon/__init__.py
rescriptoon/_actions.py
rescriptoon/_cli.py
rescriptoon/_keys.py
rescriptoon/_mapping.py
rescriptoon/_ui.py
rescriptoon-1.0.0.dist-info/COPYING
rescriptoon-1.0.0.dist-info/METADATA
rescriptoon-1.0.0.dist-info/WHEEL
rescriptoon-1.0.0.dist-info/entry_points.txt
rescriptoon-1.0.0.dist-info/top_level.txt
rescriptoon-1.0.0.dist-info/RECORD
