Metadata-Version: 2.1
Name: rescriptoon
Version: 1.0.0
Summary: Control one or two Toons in Toontown Rewritten via keyboard
Home-page: https://git.hammerle.me/fphammerle/rescriptoon
Author: Fabian Peter Hammerle
Author-email: fabian@hammerle.me
License: GPLv3+
Keywords: control,game,keyboard,toontown rewritten,ttr
Platform: UNKNOWN
Classifier: Development Status :: 4 - Beta
Classifier: Intended Audience :: End Users/Desktop
Classifier: License :: OSI Approved :: GNU General Public License v3 or later (GPLv3+)
Classifier: Operating System :: POSIX :: Linux
Classifier: Programming Language :: Python :: 3
Classifier: Topic :: Games/Entertainment
Classifier: Topic :: Utilities
Requires-Dist: xlib
